{
    "Name": "",
    "ConnectionString": "",
    "Scope": "Server",
    "Service": {
        "SysConfigurations": [],
        "TempDBConfiguration": [],
        "TraceFlags": []
    },
    "Databases": [],
    "Security": {
        "Logins": [],
        "SysAdmins": []
    },
    "ServerObjects": {},
    "AvailabilityGroups": [],
    "Management": {
        "NumErrorLogs": 6,
        "Xevents": []
    },
    "SqlAgent": {
        "Jobs": [],
        "JobSchedules": [],
        "Alerts": [],
        "Operators": []
    }
}